pydumpi/__init__.py
pydumpi/callbacks.py
pydumpi/constants.py
pydumpi/dtypes.py
pydumpi/undumpi.py
pydumpi/util.py
pydumpi/lib/libundumpi.so.8.0.0
pydumpi-0.1.3.dist-info/METADATA
pydumpi-0.1.3.dist-info/RECORD
pydumpi-0.1.3.dist-info/WHEEL
pydumpi-0.1.3.dist-info/top_level.txt
