Metadata-Version: 2.1
Name: pydumpi
Version: 0.1.3
Summary: Python bindings for the sst-dumpi trace format.
Home-page: https://github.com/justacid/pydumpi
Author: Tobias Schwackenhofer
Author-email: tobiasschw@gmail.com
License: UNKNOWN
Platform: UNKNOWN
Classifier: Programming Language :: Python :: 3
Classifier: License :: OSI Approved :: MIT License
Classifier: Operating System :: POSIX :: Linux
Requires-Python: >=3.4
